paraphrasel/__init__.py
paraphrasel/cli.py
paraphrasel/match.py
paraphrasel/semantic_similarity.py
paraphrasel/util.py
paraphrasel-0.0.2.dist-info/LICENSE.md
paraphrasel-0.0.2.dist-info/METADATA
paraphrasel-0.0.2.dist-info/WHEEL
paraphrasel-0.0.2.dist-info/entry_points.txt
paraphrasel-0.0.2.dist-info/top_level.txt
paraphrasel-0.0.2.dist-info/RECORD
