Metadata-Version: 2.1
Name: paraphrasel
Version: 0.0.2
Summary: Match word semantic similarity
Author-email: Reinier Koops <reinier.koops@outlook.com>
License: The MIT License (MIT)
Project-URL: Documentation, https://reinierkoops.github.io/paraphrasel/
Project-URL: Repository, https://github.com/ReinierKoops/paraphrasel.git
Project-URL: Changelog, https://github.com/ReinierKoops/paraphrasel/releases
Classifier: License :: OSI Approved :: MIT License
Classifier: Operating System :: OS Independent
Classifier: Programming Language :: Python
Classifier: Programming Language :: Python :: 3
Classifier: Programming Language :: Python :: 3.10
Classifier: Programming Language :: Python :: 3.11
Classifier: Programming Language :: Python :: 3.12
Classifier: Programming Language :: Python :: 3 :: Only
Requires-Python: >=3.10
License-File: LICENSE.md
Requires-Dist: torch>=2.5.0
Requires-Dist: sentence_transformers>=3.0.0
Requires-Dist: click>=8.0.0
Provides-Extra: dev
Requires-Dist: black>=24.0.0; extra == "dev"
Requires-Dist: pytest>=8.0.0; extra == "dev"
Requires-Dist: isort>=5.0.0; extra == "dev"
Requires-Dist: pre-commit>=4.0.0; extra == "dev"
Requires-Dist: ruff>=0.8.0; extra == "dev"
Requires-Dist: mkdocs>=1.6.0; extra == "dev"
Requires-Dist: mkdocs-material>=9.0.0; extra == "dev"
